odoo10_addon_delivery_carrier_default_tracking_url-10.0.1.1.0-py3.6-nspkg.pth
odoo/addons/delivery_carrier_default_tracking_url/README.rst
odoo/addons/delivery_carrier_default_tracking_url/__init__.py
odoo/addons/delivery_carrier_default_tracking_url/__manifest__.py
odoo/addons/delivery_carrier_default_tracking_url/i18n/delivery_carrier_default_tracking_url.pot
odoo/addons/delivery_carrier_default_tracking_url/models/__init__.py
odoo/addons/delivery_carrier_default_tracking_url/models/delivery_carrier.py
odoo/addons/delivery_carrier_default_tracking_url/models/sale_order.py
odoo/addons/delivery_carrier_default_tracking_url/models/stock_picking.py
odoo/addons/delivery_carrier_default_tracking_url/readme/CONTRIBUTORS.rst
odoo/addons/delivery_carrier_default_tracking_url/readme/DESCRIPTION.rst
odoo/addons/delivery_carrier_default_tracking_url/readme/USAGE.rst
odoo/addons/delivery_carrier_default_tracking_url/static/description/icon.png
odoo/addons/delivery_carrier_default_tracking_url/static/description/index.html
odoo/addons/delivery_carrier_default_tracking_url/views/delivery_carrier.xml
odoo/addons/delivery_carrier_default_tracking_url/views/sale_order.xml
odoo/addons/delivery_carrier_default_tracking_url/views/stock_picking.xml
odoo10_addon_delivery_carrier_default_tracking_url-10.0.1.1.0.dist-info/METADATA
odoo10_addon_delivery_carrier_default_tracking_url-10.0.1.1.0.dist-info/WHEEL
odoo10_addon_delivery_carrier_default_tracking_url-10.0.1.1.0.dist-info/namespace_packages.txt
odoo10_addon_delivery_carrier_default_tracking_url-10.0.1.1.0.dist-info/top_level.txt
odoo10_addon_delivery_carrier_default_tracking_url-10.0.1.1.0.dist-info/RECORD
