Metadata-Version: 2.1
Name: odoo10-addon-delivery-carrier-default-tracking-url
Version: 10.0.1.1.0
Summary: Adds the default tracking url on delivery carrier
Home-page: https://github.com/OCA/delivery-carrier
Author: ACSONE SA/NV,Odoo Community Association (OCA)
Author-email: support@odoo-community.org
License: AGPL-3
Platform: UNKNOWN
Classifier: Programming Language :: Python
Classifier: Framework :: Odoo
Classifier: License :: OSI Approved :: GNU Affero General Public License v3
Classifier: Development Status :: 3 - Alpha
Requires-Python: ~=2.7
Requires-Dist: odoo (<10.1dev,>=10.0)
